{
  "condition": "minecraft:all_of",
  "terms": [
    {
      "condition": "minecraft:location_check",
      "offsetX": 0,
      "offsetY": -1,
      "offsetZ": 0,
      "predicate": {
        "block": {
          "blocks": [
            "minecraft:obsidian"
          ]
        }
      }
    },
    {
      "condition": "minecraft:location_check",
      "offsetX": 1,
      "offsetY": -1,
      "offsetZ": 0,
      "predicate": {
        "block": {
          "blocks": [
            "minecraft:crying_obsidian"
          ]
        }
      }
    },
    {
      "condition": "minecraft:location_check",
      "offsetX": 0,
      "offsetY": -1,
      "offsetZ": 1,
      "predicate": {
        "block": {
          "blocks": [
            "minecraft:crying_obsidian"
          ]
        }
      }
    },
    {
      "condition": "minecraft:location_check",
      "offsetX": -1,
      "offsetY": -1,
      "offsetZ": 0,
      "predicate": {
        "block": {
          "blocks": [
            "minecraft:crying_obsidian"
          ]
        }
      }
    },
    {
      "condition": "minecraft:location_check",
      "offsetX": 0,
      "offsetY": -1,
      "offsetZ": -1,
      "predicate": {
        "block": {
          "blocks": [
            "minecraft:crying_obsidian"
          ]
        }
      }
    },
    {
      "condition": "minecraft:location_check",
      "offsetX": 2,
      "offsetY": -1,
      "offsetZ": 0,
      "predicate": {
        "block": {
          "blocks": [
            "minecraft:amethyst_block"
          ]
        }
      }
    },
    {
      "condition": "minecraft:location_check",
      "offsetX": 1,
      "offsetY": -1,
      "offsetZ": 1,
      "predicate": {
        "block": {
          "blocks": [
            "minecraft:amethyst_block"
          ]
        }
      }
    },
    {
      "condition": "minecraft:location_check",
      "offsetX": 0,
      "offsetY": -1,
      "offsetZ": 2,
      "predicate": {
        "block": {
          "blocks": [
            "minecraft:amethyst_block"
          ]
        }
      }
    },
    {
      "condition": "minecraft:location_check",
      "offsetX": -1,
      "offsetY": -1,
      "offsetZ": 1,
      "predicate": {
        "block": {
          "blocks": [
            "minecraft:amethyst_block"
          ]
        }
      }
    },
    {
      "condition": "minecraft:location_check",
      "offsetX": -2,
      "offsetY": -1,
      "offsetZ": 0,
      "predicate": {
        "block": {
          "blocks": [
            "minecraft:amethyst_block"
          ]
        }
      }
    },
    {
      "condition": "minecraft:location_check",
      "offsetX": -1,
      "offsetY": -1,
      "offsetZ": -1,
      "predicate": {
        "block": {
          "blocks": [
            "minecraft:amethyst_block"
          ]
        }
      }
    },
    {
      "condition": "minecraft:location_check",
      "offsetX": 0,
      "offsetY": -1,
      "offsetZ": -2,
      "predicate": {
        "block": {
          "blocks": [
            "minecraft:amethyst_block"
          ]
        }
      }
    },
    {
      "condition": "minecraft:location_check",
      "offsetX": 1,
      "offsetY": -1,
      "offsetZ": -1,
      "predicate": {
        "block": {
          "blocks": [
            "minecraft:amethyst_block"
          ]
        }
      }
    }
  ]
}